adcami/__init__.py
adcami/adcami.py
adcami-0.1.2.dist-info/LICENSE
adcami-0.1.2.dist-info/METADATA
adcami-0.1.2.dist-info/WHEEL
adcami-0.1.2.dist-info/entry_points.txt
adcami-0.1.2.dist-info/top_level.txt
adcami-0.1.2.dist-info/RECORD
