Metadata-Version: 2.1
Name: adcami
Version: 0.1.2
Summary: UNKNOWN
Home-page: https://github.com/sumanth-lingappa/adcami
Author: Sumanth Lingappa
Author-email: sumanth.lingappa@gmail.com
License: UNKNOWN
Keywords: citrix adc,aws ami,latest aws citrix adc ami
Platform: UNKNOWN
Classifier: Programming Language :: Python :: 3
Classifier: License :: OSI Approved :: MIT License
Classifier: Operating System :: OS Independent
Requires-Python: >=3.6
Requires-Dist: appdirs (==1.4.4)
Requires-Dist: black (==21.7b0)
Requires-Dist: boto3 (==1.17.109)
Requires-Dist: botocore (==1.20.109)
Requires-Dist: click (==8.0.1)
Requires-Dist: jmespath (==0.10.0)
Requires-Dist: mypy-extensions (==0.4.3)
Requires-Dist: pathspec (==0.9.0)
Requires-Dist: python-dateutil (==2.8.1)
Requires-Dist: regex (==2021.7.6)
Requires-Dist: s3transfer (==0.4.2)
Requires-Dist: six (==1.16.0)
Requires-Dist: tomli (==1.0.4)
Requires-Dist: urllib3 (==1.26.6)
